cacao/__init__.py
cacao/desktop.py
cacao/cli/__init__.py
cacao/cli/codegen.py
cacao/cli/commands.py
cacao/cli/templates/cacao.json
cacao/cli/templates/docs/CORE_ARCH.md
cacao/core/__init__.py
cacao/core/app.py
cacao/core/component_compiler.py
cacao/core/decorators.py
cacao/core/diffing.py
cacao/core/pwa.py
cacao/core/server.py
cacao/core/session.py
cacao/core/state.py
cacao/core/theme.py
cacao/core/mixins/__init__.py
cacao/core/mixins/documentation.py
cacao/core/mixins/logging.py
cacao/core/mixins/validation.py
cacao/core/static/index.html
cacao/core/static/css/base.css
cacao/core/static/css/cacao-components.css
cacao/core/static/css/icon-styles.css
cacao/core/static/css/react-components.css
cacao/core/static/icons/bean.svg
cacao/core/static/icons/cacao.svg
cacao/core/static/icons/chef-hat.svg
cacao/core/static/icons/cloud.svg
cacao/core/static/icons/cocoa-tree.svg
cacao/core/static/icons/db.svg
cacao/core/static/icons/fire.svg
cacao/core/static/icons/grinder.svg
cacao/core/static/icons/home.svg
cacao/core/static/icons/hot-drink.svg
cacao/core/static/icons/icon-192.png
cacao/core/static/icons/icon-512.png
cacao/core/static/icons/icons.ai
cacao/core/static/icons/menu.svg
cacao/core/static/icons/settings.svg
cacao/core/static/icons/star.svg
cacao/core/static/icons/trash.svg
cacao/core/static/icons/user.svg
cacao/core/static/icons/whisk.svg
cacao/core/static/js/cacao-components.js
cacao/core/static/js/cacao-core.js
cacao/core/static/js/react-bridge.js
cacao/core/static/js/theme-loader.js
cacao/core/static/js/websocket.js
cacao/extensions/__init__.py
cacao/extensions/react_extension.py
cacao/extensions/auth/__init__.py
cacao/extensions/metrics/__init__.py
cacao/extensions/plugins/__init__.py
cacao/extensions/plugins/pandas_table/__init__.py
cacao/extensions/plugins/pandas_table/converter.py
cacao/extensions/plugins/pandas_table/plugin.py
cacao/plugins/__init__.py
cacao/plugins/base_plugin.py
cacao/plugins/html_renderer.py
cacao/plugins/markdown_renderer.py
cacao-1.0.40.dist-info/METADATA
cacao-1.0.40.dist-info/WHEEL
cacao-1.0.40.dist-info/entry_points.txt
cacao-1.0.40.dist-info/top_level.txt
cacao-1.0.40.dist-info/RECORD
