Metadata-Version: 2.4
Name: cacao
Version: 1.0.40
Summary: Cacao is a high-performance, reactive web framework for Python, designed to simplify building interactive dashboards and data apps.
Home-page: https://github.com/cacao-research/Cacao
Author: Juan Denis
Author-email: Juan@vene.co
License: MIT
Classifier: Programming Language :: Python :: 3
Classifier: License :: OSI Approved :: MIT License
Classifier: Operating System :: OS Independent
Requires-Python: >=3.7
Requires-Dist: websockets
Requires-Dist: asyncio
Requires-Dist: watchfiles
Requires-Dist: colorama
Requires-Dist: pywebview>=4.0.2
Dynamic: author
Dynamic: author-email
Dynamic: classifier
Dynamic: description
Dynamic: description-content-type
Dynamic: home-page
Dynamic: license
Dynamic: requires-dist
Dynamic: requires-python
Dynamic: summary
